pyviralcontent/__init__.py
pyviralcontent/content_analyzer.py
pyviralcontent/likert_scale.py
pyviralcontent/readability_calculator.py
pyviralcontent/syllable_counter.py
pyviralcontent/text_analyzer.py
pyviralcontent/visualizer.py
pyviralcontent-0.1.5.dist-info/METADATA
pyviralcontent-0.1.5.dist-info/WHEEL
pyviralcontent-0.1.5.dist-info/top_level.txt
pyviralcontent-0.1.5.dist-info/RECORD
