Metadata-Version: 2.1
Name: pyviralcontent
Version: 0.1.5
Summary: A package for analyzing content readability and virality potential.
Home-page: https://github.com/bhaskatripathi/pyviralcontent
Author: Bhaskar Tripathi
Author-email: bhaskar.tripathi@gmail.com
Keywords: readability virality content-analysis
Requires-Dist: pandas
Requires-Dist: numpy
Requires-Dist: matplotlib
Requires-Dist: seaborn
